[
  {
    "name": "Aries",
    "code": "R01",
    "description": "The Ram",
    "symbol": "♈",
    "number": 1,
    "elementPanchamahabhuta": "Fire",
    "quality": "Movable",
    "gender": "Male",
    "ruler": "MA",
    "exaltedPlanet": "SU",
    "debilitatedPlanet": "SA",
    "moolatrikonaPlanet": "MA",
    "bodyParts": [
      "Head",
      "Face",
      "Brain"
    ],
    "nature": "Cruel",
    "caste": "Kshatriya",
    "guna": "Rajasic",
    "direction": "East",
    "color": "Red",
    "lifespan": "Short",
    "varna": "Fire",
    "animal": "Ram",
    "duration": "Short Ascension",
    "fertile": false,
    "humanAnimal": "Quadruped",
    "keywords": [
      "Initiative",
      "Courage",
      "Leadership",
      "Impulsive",
      "Independent",
      "Pioneer"
    ],
    "represents": [
      "Beginning",
      "Action",
      "Energy",
      "Aggression",
      "Passion",
      "Self"
    ]
  },
  {
    "name": "Taurus",
    "code": "R02",
    "description": "The Bull",
    "symbol": "♉",
    "number": 2,
    "elementPanchamahabhuta": "EA",
    "quality": "Fixed",
    "gender": "Female",
    "ruler": "VE",
    "exaltedPlanet": "MO",
    "debilitatedPlanet": "",
    "moolatrikonaPlanet": "VE",
    "bodyParts": [
      "Neck",
      "Throat",
      "Vocal Cords"
    ],
    "nature": "Mild",
    "caste": "Vaishya",
    "guna": "Rajasic",
    "direction": "South",
    "color": "White",
    "lifespan": "Long",
    "varna": "EA",
    "animal": "Bull",
    "duration": "Short Ascension",
    "fertile": true,
    "humanAnimal": "Quadruped",
    "keywords": [
      "Stability",
      "Material",
      "Sensual",
      "Stubborn",
      "Patient",
      "Practical"
    ],
    "represents": [
      "Wealth",
      "Resources",
      "Values",
      "Stability",
      "Possessions",
      "Comfort"
    ]
  },
  {
    "name": "Gemini",
    "code": "R03",
    "description": "The Twins",
    "symbol": "♊",
    "number": 3,
    "elementPanchamahabhuta": "Air",
    "quality": "Dual",
    "gender": "Male",
    "ruler": "ME",
    "exaltedPlanet": "RA",
    "debilitatedPlanet": "",
    "moolatrikonaPlanet": "",
    "bodyParts": [
      "Shoulders",
      "Arms",
      "Hands"
    ],
    "nature": "Mild",
    "caste": "Shudra",
    "guna": "Rajasic",
    "direction": "West",
    "color": "Green",
    "lifespan": "Long",
    "varna": "Air",
    "animal": "Human",
    "duration": "Long Ascension",
    "fertile": true,
    "humanAnimal": "Human",
    "keywords": [
      "Communication",
      "Versatile",
      "Curious",
      "Intellectual",
      "Adaptable",
      "Dual"
    ],
    "represents": [
      "Communication",
      "Intelligence",
      "Siblings",
      "Short Travels",
      "Learning",
      "Information"
    ]
  },
  {
    "name": "Cancer",
    "code": "R04",
    "description": "The Crab",
    "symbol": "♋",
    "number": 4,
    "elementPanchamahabhuta": "Water",
    "quality": "Movable",
    "gender": "Female",
    "ruler": "MO",
    "exaltedPlanet": "JU",
    "debilitatedPlanet": "MA",
    "moolatrikonaPlanet": "",
    "bodyParts": [
      "Chest",
      "Breasts",
      "Stomach"
    ],
    "nature": "Mild",
    "caste": "Brahmin",
    "guna": "Sattvic",
    "direction": "North",
    "color": "Milky White",
    "lifespan": "Medium",
    "varna": "Water",
    "animal": "Insect",
    "duration": "Long Ascension",
    "fertile": true,
    "humanAnimal": "Water Creature",
    "keywords": [
      "Nurturing",
      "Emotional",
      "Protective",
      "Sensitive",
      "Home",
      "Mother"
    ],
    "represents": [
      "Home",
      "Mother",
      "Emotions",
      "Security",
      "Nurturing",
      "Comfort"
    ]
  },
  {
    "name": "Leo",
    "code": "R05",
    "description": "The Lion",
    "symbol": "♌",
    "number": 5,
    "elementPanchamahabhuta": "Fire",
    "quality": "Fixed",
    "gender": "Male",
    "ruler": "SU",
    "exaltedPlanet": "",
    "debilitatedPlanet": "",
    "moolatrikonaPlanet": "SU",
    "bodyParts": [
      "Heart",
      "Upper Back",
      "Spine"
    ],
    "nature": "Cruel",
    "caste": "Kshatriya",
    "guna": "Sattvic",
    "direction": "East",
    "color": "Golden",
    "lifespan": "Medium",
    "varna": "Fire",
    "animal": "Quadruped",
    "duration": "Long Ascension",
    "fertile": true,
    "humanAnimal": "Quadruped",
    "keywords": [
      "Leadership",
      "Pride",
      "Creative",
      "Generous",
      "Dramatic",
      "Authority"
    ],
    "represents": [
      "Self-expression",
      "Creativity",
      "Children",
      "Romance",
      "Entertainment",
      "Fame"
    ]
  },
  {
    "name": "Virgo",
    "code": "R06",
    "description": "The Maiden",
    "symbol": "♍",
    "number": 6,
    "elementPanchamahabhuta": "EA",
    "quality": "Dual",
    "gender": "Female",
    "ruler": "ME",
    "exaltedPlanet": "ME",
    "debilitatedPlanet": "VE",
    "moolatrikonaPlanet": "ME",
    "bodyParts": [
      "Intestines",
      "Abdomen",
      "Digestive System"
    ],
    "nature": "Mild",
    "caste": "Vaishya",
    "guna": "Rajasic",
    "direction": "South",
    "color": "Variegated",
    "lifespan": "Medium",
    "varna": "EA",
    "animal": "Human",
    "duration": "Long Ascension",
    "fertile": true,
    "humanAnimal": "Human",
    "keywords": [
      "Analytical",
      "Service",
      "Practical",
      "Detail-oriented",
      "Health",
      "Perfectionist"
    ],
    "represents": [
      "Service",
      "Health",
      "Work",
      "Daily Routine",
      "Analysis",
      "Improvement"
    ]
  },
  {
    "name": "Libra",
    "code": "R07",
    "description": "The Scales",
    "symbol": "♎",
    "number": 7,
    "elementPanchamahabhuta": "Air",
    "quality": "Movable",
    "gender": "Male",
    "ruler": "VE",
    "exaltedPlanet": "SA",
    "debilitatedPlanet": "SU",
    "moolatrikonaPlanet": "VE",
    "bodyParts": [
      "Kidneys",
      "Lower Back",
      "Lumbar Region"
    ],
    "nature": "Mild",
    "caste": "Shudra",
    "guna": "Rajasic",
    "direction": "West",
    "color": "Variegated",
    "lifespan": "Short",
    "varna": "Air",
    "animal": "Human",
    "duration": "Short Ascension",
    "fertile": false,
    "humanAnimal": "Human",
    "keywords": [
      "Balance",
      "Harmony",
      "Relationships",
      "Justice",
      "Diplomatic",
      "Partnership"
    ],
    "represents": [
      "Partnership",
      "Marriage",
      "Balance",
      "Justice",
      "Others",
      "Harmony"
    ]
  },
  {
    "name": "Scorpio",
    "code": "R08",
    "description": "The Scorpion",
    "symbol": "♏",
    "number": 8,
    "elementPanchamahabhuta": "Water",
    "quality": "Fixed",
    "gender": "Female",
    "ruler": "MA",
    "exaltedPlanet": "",
    "debilitatedPlanet": "MO",
    "moolatrikonaPlanet": "",
    "bodyParts": [
      "Reproductive Organs",
      "Genitals",
      "Pelvis"
    ],
    "nature": "Cruel",
    "caste": "Brahmin",
    "guna": "Tamasic",
    "direction": "North",
    "color": "Red/Brown",
    "lifespan": "Medium",
    "varna": "Water",
    "animal": "Insect",
    "duration": "Short Ascension",
    "fertile": true,
    "humanAnimal": "Insect",
    "keywords": [
      "Intensity",
      "Transformation",
      "Secretive",
      "Passionate",
      "Mysterious",
      "Power"
    ],
    "represents": [
      "Transformation",
      "Death",
      "Rebirth",
      "Occult",
      "Secrets",
      "Inheritance"
    ]
  },
  {
    "name": "Sagittarius",
    "code": "R09",
    "description": "The Archer",
    "symbol": "♐",
    "number": 9,
    "elementPanchamahabhuta": "Fire",
    "quality": "Dual",
    "gender": "Male",
    "ruler": "JU",
    "exaltedPlanet": "KE",
    "debilitatedPlanet": "",
    "moolatrikonaPlanet": "JU",
    "bodyParts": [
      "Thighs",
      "Hips",
      "Liver"
    ],
    "nature": "Mild",
    "caste": "Kshatriya",
    "guna": "Sattvic",
    "direction": "East",
    "color": "Yellow",
    "lifespan": "Medium",
    "varna": "Fire",
    "animal": "Half-human Half-animal",
    "duration": "Long Ascension",
    "fertile": true,
    "humanAnimal": "Centaur",
    "keywords": [
      "Philosophy",
      "Wisdom",
      "Adventure",
      "Optimistic",
      "Freedom",
      "Higher Learning"
    ],
    "represents": [
      "Higher Education",
      "Philosophy",
      "Religion",
      "Long Travels",
      "Fortune",
      "Wisdom"
    ]
  },
  {
    "name": "Capricorn",
    "code": "R10",
    "description": "The Goat",
    "symbol": "♑",
    "number": 10,
    "elementPanchamahabhuta": "EA",
    "quality": "Movable",
    "gender": "Female",
    "ruler": "SA",
    "exaltedPlanet": "MA",
    "debilitatedPlanet": "JU",
    "moolatrikonaPlanet": "",
    "bodyParts": [
      "Knees",
      "Bones",
      "Joints"
    ],
    "nature": "Mild",
    "caste": "Vaishya",
    "guna": "Tamasic",
    "direction": "South",
    "color": "Variegated",
    "lifespan": "Long",
    "varna": "EA",
    "animal": "Half-water Half-land",
    "duration": "Long Ascension",
    "fertile": false,
    "humanAnimal": "Water Creature",
    "keywords": [
      "Ambition",
      "Discipline",
      "Practical",
      "Responsible",
      "Career",
      "Structure"
    ],
    "represents": [
      "Career",
      "Status",
      "Ambition",
      "Discipline",
      "Authority",
      "Achievement"
    ]
  },
  {
    "name": "Aquarius",
    "code": "R11",
    "description": "The Water Bearer",
    "symbol": "♒",
    "number": 11,
    "elementPanchamahabhuta": "Air",
    "quality": "Fixed",
    "gender": "Male",
    "ruler": "SA",
    "exaltedPlanet": "",
    "debilitatedPlanet": "",
    "moolatrikonaPlanet": "SA",
    "bodyParts": [
      "Ankles",
      "Calves",
      "Circulatory System"
    ],
    "nature": "Mild",
    "caste": "Shudra",
    "guna": "Tamasic",
    "direction": "West",
    "color": "Black",
    "lifespan": "Long",
    "varna": "Air",
    "animal": "Human",
    "duration": "Long Ascension",
    "fertile": false,
    "humanAnimal": "Human",
    "keywords": [
      "Innovation",
      "Humanitarian",
      "Unconventional",
      "Independent",
      "Social",
      "Progressive"
    ],
    "represents": [
      "Community",
      "Friends",
      "Goals",
      "Innovation",
      "Humanitarian",
      "Social Groups"
    ]
  },
  {
    "name": "Pisces",
    "code": "R12",
    "description": "The Fish",
    "symbol": "♓",
    "number": 12,
    "elementPanchamahabhuta": "Water",
    "quality": "Dual",
    "gender": "Female",
    "ruler": "JU",
    "exaltedPlanet": "VE",
    "debilitatedPlanet": "ME",
    "moolatrikonaPlanet": "",
    "bodyParts": [
      "Feet",
      "Toes",
      "Lymphatic System"
    ],
    "nature": "Mild",
    "caste": "Brahmin",
    "guna": "Sattvic",
    "direction": "North",
    "color": "Light Yellow",
    "lifespan": "Short",
    "varna": "Water",
    "animal": "Water creature",
    "duration": "Long Ascension",
    "fertile": true,
    "humanAnimal": "Water Creature",
    "keywords": [
      "Compassion",
      "Spiritual",
      "Intuitive",
      "Dreamy",
      "Mystical",
      "Sacrificial"
    ],
    "represents": [
      "Spirituality",
      "Moksha",
      "Isolation",
      "Mysticism",
      "Compassion",
      "Dissolution"
    ]
  }
]